{

  "areas": [
    {
      "name": "Tyre",
      "options": ["Outside Camp", "Inside Camp"],
      "camps": [
        "Rashidieh Palestinian Refugee Camp",
        "El Buss Palestinian Refugee Camp",
        "Burj El Shemali Palestinian Refugee Camp"
      ]
    },
    {
      "name": "Saida",
      "options": ["Outside Camp", "Inside Camp"],
      "camps": [
        "Mieh Mieh Palestinian Refugee Camp",
        "Ein El Hilweh Palestinian Refugee Camp"
      ]
    },
    {
      "name": "North Lebanon",
      "options": ["Outside Camp", "Inside Camp"],
      "camps": [
        "Nahr El Bared Palestinian Refugee Camp",
        "Baddawi Palestinian Refugee Camp"
      ]
    },
    {
      "name": "Beqaa",
      "options": ["Outside Camp", "Inside Camp"],
      "camps": ["Wavel Palestinian Refugee Camp"]
    },
    {
      "name": "Beirut and Mount Lebanon",
      "options": ["Outside Camp", "Inside Camp"],
      "camps": [
        "Shatila Palestinian Refugee Camp",
        "Mar Elias Palestinian Refugee Camp",
        "Dbayeh Palestinian Refugee Camp",
        "Burj El Barajneh Palestinian Camp"
      ]
    }
  ],
  "majors": [
    "Translation",
    "Theatre Arts",
    "Teaching Diploma",
    "Statistics",
    "Speech Therapy",
    "Special Education Diploma",
    "Sociology",
    "Religion",
    "Radio Television",
    "Public Relations",
    "Public Health",
    "Psychology",
    "Political Science",
    "Physiotherapy",
    "Physics",
    "Philosophy",
    "Pharmacy",
    "Occupational Therapy",
    "Nursing",
    "Medical Lab Sciences",
    "Mechanical Engineering",
    "Mathematics",
    "Mass Communication",
    "Marketing",
    "Management Information Systems",
    "Law",
    "Journalism",
    "International Relations Affairs",
    "International Business Management",
    "Interior Design",
    "Interior Architecture",
    "Industrial Engineering",
    "Human Resources Management",
    "Hospitality,Tourism, Travel",
    "History",
    "Graphic Design",
    "Geography",
    "French Literature",
    "Food Science & Safety",
    "Food Nutrition",
    "Finance",
    "Fashion Design",
    "Environmental Science",
    "English Literature",
    "Electrical Engineering",
    "Early Childhood Education",
    "Design Visual Communications",
    "Dentistry",
    "Computer Science Programming",
    "Computer Networking",
    "Computer Engineering",
    "Computer and Communication Engineering",
    "Civil Engineering",
    "Cinematography",
    "Chemistry",
    "Chemical Engineering",
    "Business Administration Management",
    "Biomedical Engineering",
    "Biology",
    "Biochemistry",
    "Art History",
    "Architectural Engineering",
    "Arabic Literature",
    "Agriculture Engineering",
    "Accounting Information System",
    "Accounting"
  ],
  "Role":[
    "Admin",
    "Employer",
    "Youth"
  ],
  "genderOptions": ["Male", "Female"],
  "nationalityOptions": [
    "Palestinian Refugee in Lebanon",
    "Palestinian Refugee from Syria",
    "Lebanese",
    "Syrian",
    "Non-ID"
  ],
  "registrationStatusOptions": [
    "Registered",
    "Not Registered",
    "Palestinian Not-ID"
  ],
  "headfaOptions": ["Father", "Mother", "Husband", "Brother", "Sister", "Me"],
  "relationshipOptions": ["Parent", "Partner", "Sibling"],
  "employmentOpportunitiesOptions": [
    "Short-term employment opportunities with external organizations",
    "Short-term employment opportunities in UNRWA",
    "Both"
  ],
  "jobOpportunityOptions": [
    "WhatsApp Message from Employment Services Team",
    "WhatsApp Message from Area Offices",
    "UNRWA's Facebook Page",
    "NGOs",
    "Friends"
  ],
  "educationLevels": [
    "University Degree, Technical Licence (LT), University Diploma",
    "Short Term Course, Experience Work Certificate, or Diploma from Siblin Training Center",
    "Technical Baccalaureate (BT) or equivalent from Siblin Training Center (STC)",
    "Higher Technical Degree (TS) or equivalent from Siblin Training Center (STC)"
  ],
  "youthStatus": [
    "accepted",
    "rejected",
    "pending",
    "waiting"
  ]


  }

